appconf/__init__.py
appconf/base.py
appconf/utils.py
django_appconf-1.0.6.dist-info/AUTHORS
django_appconf-1.0.6.dist-info/LICENSE
django_appconf-1.0.6.dist-info/METADATA
django_appconf-1.0.6.dist-info/WHEEL
django_appconf-1.0.6.dist-info/top_level.txt
django_appconf-1.0.6.dist-info/RECORD
